<menues>
	<menu>
		<name>activation</name>
		<isStarting>true</isStarting>
		<texts>
			<text>Connect to Database</text>
		</texts>
		<fields>
			<field>User</field>
			<field>Password</field>
			<field>Database</field>
		</fields>
		<buttons>
			<button>
				<text>Connect</text>
				<helper>tourists.helpers.ButtonConnecter</helper>
				<param>activity</param>
			</button>
		</buttons>
	</menu>
	<menu>
		<name>activity</name>
		<texts>
			<text>Choose activity</text>
		</texts>
		<buttons>
			<button>
				<text>Reset database</text>
				<helper>tourists.helpers.ButtonResetter</helper>
				<param>ADMINISTRATOR_19212</param>
			</button>
			<button>
				<text>Set test database</text>
				<helper>tourists.helpers.ButtonTest</helper>
				<param>ADMINISTRATOR_19212</param>
			</button>
			<button>
				<text>Select information</text>
				<helper>tourists.helpers.ButtonMenuChanger</helper>
				<param>select TOURIST</param>
			</button>
			<button>
				<text>Edit information</text>
				<helper>tourists.helpers.ButtonMenuChanger</helper>
				<param>edit</param>
			</button>
			<button>
				<text>Disconnect</text>
				<helper>tourists.helpers.ButtonDisconnecter</helper>
				<param>activation</param>
			</button>
		</buttons>
	</menu>
	<menu>
		<name>select</name>
		<texts>
			<text>Choose what you want to select</text>
		</texts>
		<buttons>
			<button>
				<text>Tourists</text>
				<helper>tourists.helpers.ButtonMenuChanger</helper>
				<param>select_tourists</param>
			</button>
			<button>
				<text>Coaches</text>
				<helper>tourists.helpers.ButtonMenuChanger</helper>
				<param>select_coaches</param>
			</button>
			<button>
				<text>Directors</text>
				<helper>tourists.helpers.ButtonMenuChanger</helper>
				<param>select_directors</param>
			</button>
			<button>
				<text>Competitions</text>
				<helper>tourists.helpers.ButtonMenuChanger</helper>
				<param>select_competitions</param>
			</button>
			<button>
				<text>Coaches time</text>
				<helper>tourists.helpers.ButtonMenuChanger</helper>
				<param>select_coaches_time</param>
			</button>
			<button>
				<text>Routes</text>
				<helper>tourists.helpers.ButtonMenuChanger</helper>
				<param>select_routes</param>
			</button>
			<button>
				<text>Instructors</text>
				<helper>tourists.helpers.ButtonMenuChanger</helper>
				<param>select_instructors</param>
			</button>
			<button>
				<text>Back</text>
				<helper>tourists.helpers.ButtonMenuChanger</helper>
				<param>activity</param>
			</button>
		</buttons>
	</menu>
	<menu>
		<name>edit</name>
		<texts>
			<text>Choose what you want to edit</text>
		</texts>
		<buttons>
			<button>
				<text>Tourists</text>
				<helper>tourists.helpers.ButtonToEditionMenu</helper>
				<param>tourists.helpers.TouristsHelper SECTIONS_DIRECTOR</param>
			</button>
			<button>
				<text>Sportsmen</text>
				<helper>tourists.helpers.ButtonToEditionMenu</helper>
				<param>tourists.helpers.SportsmenHelper SECTIONS_DIRECTOR</param>
			</button>
			<button>
				<text>Coaches</text>
				<helper>tourists.helpers.ButtonToEditionMenu</helper>
				<param>tourists.helpers.CoachesHelper SECTIONS_DIRECTOR</param>
			</button>
			<button>
				<text>Directors</text>
				<helper>tourists.helpers.ButtonToEditionMenu</helper>
				<param>tourists.helpers.DirectorsHelper SECTIONS_DIRECTOR</param>
			</button>
			<button>
				<text>Sections</text>
				<helper>tourists.helpers.ButtonToEditionMenu</helper>
				<param>tourists.helpers.SectionsHelper SECTIONS_DIRECTOR</param>
			</button>
			<button>
				<text>Groups</text>
				<helper>tourists.helpers.ButtonToEditionMenu</helper>
				<param>tourists.helpers.GroupsHelper SECTIONS_DIRECTOR</param>
			</button>
			<button>
				<text>Trainings</text>
				<helper>tourists.helpers.ButtonToEditionMenu</helper>
				<param>tourists.helpers.TrainingsHelper SECTIONS_DIRECTOR</param>
			</button>
			<button>
				<text>Trains</text>
				<helper>tourists.helpers.ButtonToEditionMenu</helper>
				<param>tourists.helpers.TrainsHelper SECTIONS_DIRECTOR</param>
			</button>
			<button>
				<text>Attendance</text>
				<helper>tourists.helpers.ButtonToEditionMenu</helper>
				<param>tourists.helpers.AttendanceHelper SECTIONS_DIRECTOR</param>
			</button>
			<button>
				<text>Competitions</text>
				<helper>tourists.helpers.ButtonToEditionMenu</helper>
				<param>tourists.helpers.CompetitionsHelper SECTIONS_DIRECTOR</param>
			</button>
			<button>
				<text>Participation</text>
				<helper>tourists.helpers.ButtonToEditionMenu</helper>
				<param>tourists.helpers.ParticipationHelper SECTIONS_DIRECTOR</param>
			</button>
			<button>
				<text>Hikes</text>
				<helper>tourists.helpers.ButtonToEditionMenu</helper>
				<param>tourists.helpers.HikesHelper SECTIONS_DIRECTOR</param>
			</button>
			<button>
				<text>Routes</text>
				<helper>tourists.helpers.ButtonToEditionMenu</helper>
				<param>tourists.helpers.RoutesHelper HIKES_DIRECTOR</param>
			</button>
			<button>
				<text>Points</text>
				<helper>tourists.helpers.ButtonToEditionMenu</helper>
				<param>tourists.helpers.PointsHelper HIKES_DIRECTOR</param>
			</button>
			<button>
				<text>Points of routes</text>
				<helper>tourists.helpers.ButtonToEditionMenu</helper>
				<param>tourists.helpers.ContainsHelper HIKES_DIRECTOR</param>
			</button>
			<button>
				<text>Checkoints</text>
				<helper>tourists.helpers.ButtonToEditionMenu</helper>
				<param>tourists.helpers.CheckpointsHelper HIKES_DIRECTOR</param>
			</button>
			<button>
				<text>Conducted hikes</text>
				<helper>tourists.helpers.ButtonToEditionMenu</helper>
				<param>tourists.helpers.ConductedHikesHelper HIKES_DIRECTOR</param>
			</button>
			<button>
				<text>Diaries</text>
				<helper>tourists.helpers.ButtonToEditionMenu</helper>
				<param>tourists.helpers.DiariesHelper HIKES_DIRECTOR</param>
			</button>
			<button>
				<text>Went to hike</text>
				<helper>tourists.helpers.ButtonToEditionMenu</helper>
				<param>tourists.helpers.WentToHikeHelper HIKES_DIRECTOR</param>
			</button>
			<button>
				<text>Back</text>
				<helper>tourists.helpers.ButtonMenuChanger</helper>
				<param>activity</param>
			</button>
		</buttons>
	</menu>
	<menu>
		<name>select_tourists</name>
		<texts>
			<text>Choose tourists filter</text>
		</texts>
		<fields>
			<field>Section</field>
			<field>Group</field>
			<field>Birth</field>
			<field>Age</field>
			<field>Hike</field>
			<field>Hikes count</field>
			<field>Route</field>
			<field>Point</field>
			<field>Category</field>
			<field>Can go to hike</field>
		</fields>
		<dropdowns>
			<dropdown>
				<mainText>Sex</mainText>
				<texts>
					<text>M</text>
					<text>W</text>
					<text> </text>
				</texts>
			</dropdown>
		</dropdowns>
		<flags>
			<flag>All routes</flag>
			<flag>Is sportsman</flag>
			<flag>Instructor is coach</flag>
		</flags>
		<buttons>
			<button>
				<text>Find</text>
				<helper>tourists.helpers.ButtonSelecter</helper>
				<param>tourists.helpers.TouristsHelper</param>
			</button>
			<button>
				<text>Back</text>
				<helper>tourists.helpers.ButtonMenuChanger</helper>
				<param>select</param>
			</button>
		</buttons>
	</menu>
	<menu>
		<name>select_coaches</name>
		<texts>
			<text>Choose coaches filter</text>
		</texts>
		<fields>
			<field>Section</field>
			<field>Age</field>
			<field>Salary</field>
			<field>Specialization</field>
			<field>Group</field>
			<field>Trains after hour</field>
			<field>Trains before hour</field>
			<field>Trains after day</field>
			<field>Trains before day</field>
		</fields>
		<dropdowns>
			<dropdown>
				<mainText>Sex</mainText>
				<texts>
					<text>M</text>
					<text>W</text>
					<text> </text>
				</texts>
			</dropdown>
		</dropdowns>
		<buttons>
			<button>
				<text>Find</text>
				<helper>tourists.helpers.ButtonSelecter</helper>
				<param>tourists.helpers.CoachesHelper</param>
			</button>
			<button>
				<text>Back</text>
				<helper>tourists.helpers.ButtonMenuChanger</helper>
				<param>select</param>
			</button>
		</buttons>
	</menu>
	<menu>
		<name>select_directors</name>
		<texts>
			<text>Choose directors filter</text>
		</texts>
		<fields>
			<field>Salary</field>
			<field>Birth</field>
			<field>Age</field>
			<field>Admission</field>
		</fields>
		<buttons>
			<button>
				<text>Find</text>
				<helper>tourists.helpers.ButtonSelecter</helper>
				<param>tourists.helpers.DirectorsHelper</param>
			</button>
			<button>
				<text>Back</text>
				<helper>tourists.helpers.ButtonMenuChanger</helper>
				<param>select</param>
			</button>
		</buttons>
	</menu>
	<menu>
		<name>select_coaches_time</name>
		<texts>
			<text>Choose coaches time filter</text>
		</texts>
		<fields>
			<field>Name</field>
			<field>Last name</field>
			<field>Birth</field>
			<field>Section</field>
			<field>Training</field>
			<field>Trains after hour</field>
			<field>Trains before hour</field>
			<field>Trains after day</field>
			<field>Trains before day</field>
		</fields>
		<buttons>
			<button>
				<text>Find</text>
				<helper>tourists.helpers.ButtonSelecter</helper>
				<param>tourists.helpers.CoachesTimeHelper</param>
			</button>
			<button>
				<text>Back</text>
				<helper>tourists.helpers.ButtonMenuChanger</helper>
				<param>select</param>
			</button>
		</buttons>
	</menu>
	<menu>
		<name>select_competitions</name>
		<texts>
			<text>Choose competitions filter</text>
		</texts>
		<fields>
			<field>Section</field>
		</fields>
		<flags>
			<flag>All sections</flag>
		</flags>
		<buttons>
			<button>
				<text>Find</text>
				<helper>tourists.helpers.ButtonSelecter</helper>
				<param>tourists.helpers.CompetitionsHelper</param>
			</button>
			<button>
				<text>Back</text>
				<helper>tourists.helpers.ButtonMenuChanger</helper>
				<param>select</param>
			</button>
		</buttons>
	</menu>
	<menu>
		<name>select_routes</name>
		<texts>
			<text>Choose routes filter</text>
		</texts>
		<fields>
			<field>Section</field>
			<field>After day</field>
			<field>Before day</field>
			<field>Instructor name</field>
			<field>Instructor last name</field>
			<field>Instructor birth</field>
			<field>Groups count</field>
			<field>Contain point</field>
			<field>Has length more than</field>
			<field>Min category</field>
		</fields>
		<buttons>
			<button>
				<text>Find</text>
				<helper>tourists.helpers.ButtonSelecter</helper>
				<param>tourists.helpers.RoutesHelper</param>
			</button>
			<button>
				<text>Back</text>
				<helper>tourists.helpers.ButtonMenuChanger</helper>
				<param>select</param>
			</button>
		</buttons>
	</menu>
	<menu>
		<name>select_instructors</name>
		<texts>
			<text>Choose instructors filter</text>
		</texts>
		<fields>
			<field>Category</field>
			<field>Hike</field>
			<field>Hikes count</field>
			<field>Route</field>
			<field>Point</field>
		</fields>
		<flags>
			<flag>Is sportsman</flag>
			<flag>Is coach</flag>
		</flags>
		<buttons>
			<button>
				<text>Find</text>
				<helper>tourists.helpers.ButtonSelecter</helper>
				<param>tourists.helpers.InstructorsHelper</param>
			</button>
			<button>
				<text>Back</text>
				<helper>tourists.helpers.ButtonMenuChanger</helper>
				<param>select</param>
			</button>
		</buttons>
	</menu>
	<menu>
		<name>to_edit</name>
		<hasTable>true</hasTable>
		<buttons>
			<button>
				<text>Create</text>
				<helper>tourists.helpers.ButtonToCreating</helper>
			</button>
			<button>
				<text>Update</text>
				<helper>tourists.helpers.ButtonToUpdating</helper>
			</button>
			<button>
				<text>Delete</text>
				<helper>tourists.helpers.ButtonDeleter</helper>
			</button>
			<button>
				<text>Back</text>
				<helper>tourists.helpers.ButtonMenuChanger</helper>
				<param>edit</param>
			</button>
		</buttons>
	</menu>
</menues>